pm_food_lib/__init__.py
pm_food_lib/db/LogDbBase.py
pm_food_lib/db/__init__.py
pm_food_lib/db/sql_db_base_class.py
pm_food_lib/mail/__init__.py
pm_food_lib/mail/aws_ses.py
pm_food_lib/utils/__init__.py
pm_food_lib/utils/constants/PM.py
pm_food_lib/utils/constants/__init__.py
pm_food_lib/utils/constants/error_codes.py
pm_food_lib/utils/constants/log_levels.py
pm_food_lib/utils/constants/parameters.py
pm_food_lib/utils/constants/platforms.py
pm_food_lib/utils/constants/products.py
pm_food_lib/utils/formats/__init__.py
pm_food_lib/utils/formats/order.py
pm_food_lib/utils/functions/__init__.py
pm_food_lib/utils/functions/general.py
pm_food_lib/utils/functions/regions.py
pm_food_lib-0.2.8.dist-info/METADATA
pm_food_lib-0.2.8.dist-info/WHEEL
pm_food_lib-0.2.8.dist-info/RECORD
