Metadata-Version: 2.1
Name: pm-food-lib
Version: 0.2.8
Summary: 
Author: Yasin Beyazlı
Author-email: 89048757+ysnbyzli@users.noreply.github.com
Requires-Python: >=3.7,<4.0
Classifier: Programming Language :: Python :: 3
Classifier: Programming Language :: Python :: 3.7
Classifier: Programming Language :: Python :: 3.8
Classifier: Programming Language :: Python :: 3.9
Classifier: Programming Language :: Python :: 3.10
Classifier: Programming Language :: Python :: 3.11
Requires-Dist: beartype (>=0.13.1,<0.14.0)
Requires-Dist: boto3 (>=1.26.115,<2.0.0)
Requires-Dist: datetime (>=5.1,<6.0)
Requires-Dist: iso8601 (>=1.1.0,<2.0.0)
Requires-Dist: mysql-connector-python (>=8.0.33,<9.0.0)
Requires-Dist: pyjwt (>=2.6.0,<3.0.0)
Requires-Dist: requests (>=2.28.2,<3.0.0)
Requires-Dist: slugify (>=0.0.1,<0.0.2)
Requires-Dist: uuid (>=1.30,<2.0)
